fastcrackle.cpython-310-x86_64-linux-gnu.so
crackle/__init__.py
crackle/array.py
crackle/codec.py
crackle/headers.py
crackle/lib.py
crackle/operations.py
crackle/util.py
crackle_cli/__init__.py
crackle_cli/cli.py
crackle_codec-0.35.1.dist-info/METADATA
crackle_codec-0.35.1.dist-info/WHEEL
crackle_codec-0.35.1.dist-info/entry_points.txt
crackle_codec-0.35.1.dist-info/pbr.json
crackle_codec-0.35.1.dist-info/top_level.txt
crackle_codec-0.35.1.dist-info/RECORD
crackle_codec-0.35.1.dist-info/licenses/AUTHORS
crackle_codec-0.35.1.dist-info/licenses/LICENSE
