Metadata-Version: 2.4
Name: crackle-codec
Version: 0.35.1
Summary: Crackle 3D dense segmentation compression codec.
Home-page: https://github.com/seung-lab/crackle
Author: William Silversmith
Author-email: ws9@princeton.edu
License: BSD-3-Clause
Classifier: Intended Audience :: Developers
Classifier: Development Status :: 4 - Beta
Classifier: Programming Language :: Python :: 3
Classifier: Programming Language :: Python :: 3.9
Classifier: Programming Language :: Python :: 3.10
Classifier: Programming Language :: Python :: 3.11
Classifier: Programming Language :: Python :: 3.12
Classifier: Programming Language :: Python :: 3.13
Classifier: Topic :: Scientific/Engineering
License-File: LICENSE
License-File: AUTHORS
Requires-Dist: fastremap
Requires-Dist: google_crc32c
Requires-Dist: numpy
Requires-Dist: pybind11
Dynamic: author
Dynamic: author-email
Dynamic: classifier
Dynamic: description
Dynamic: description-content-type
Dynamic: home-page
Dynamic: license
Dynamic: license-file
Dynamic: requires-dist
Dynamic: summary
